{"name":"Sivir's Defiants","tier":"CHALLENGER","queue":"RANKED_FLEX_TT","leagueId":"71146445-4e32-37b1-b5d4-c7dee72ea7b7","entries":[{"playerOrTeamId":"25844479","playerOrTeamName":"Heronic","leaguePoints":536,"rank":"I","wins":933,"losses":799,"veteran":false,"inactive":false,"freshBlood":false,"hotStreak":true},{"playerOrTeamId":"26328826","playerOrTeamName":"GG MaikTurtle","leaguePoints":538,"rank":"I","wins":253,"losses":168,"veteran":true,"inactive":false,"freshBlood":false,"hotStreak":true},{"playerOrTeamId":"36040196","playerOrTeamName":"MGK the greatest","leaguePoints":513,"rank":"I","wins":361,"losses":264,"veteran":true,"inactive":false,"freshBlood":false,"hotStreak":false},{"playerOrTeamId":"27451683","playerOrTeamName":"Not MMGG","leaguePoints":514,"rank":"I","wins":157,"losses":100,"veteran":false,"inactive":false,"freshBlood":true,"hotStreak":true},{"playerOrTeamId":"26990179","playerOrTeamName":"MoneyMonkeyGG","leaguePoints":660,"rank":"I","wins":197,"losses":127,"veteran":true,"inactive":false,"freshBlood":false,"hotStreak":false},{"playerOrTeamId":"19912685","playerOrTeamName":"TPS Plasma4","leaguePoints":783,"rank":"I","wins":392,"losses":240,"veteran":true,"inactive":false,"freshBlood":false,"hotStreak":false},{"playerOrTeamId":"99138718","playerOrTeamName":"BabyFakér","leaguePoints":533,"rank":"I","wins":98,"losses":33,"veteran":false,"inactive":false,"freshBlood":true,"hotStreak":false},{"playerOrTeamId":"33458277","playerOrTeamName":"MakiFelix","leaguePoints":620,"rank":"I","wins":235,"losses":160,"veteran":false,"inactive":false,"freshBlood":false,"hotStreak":false},{"playerOrTeamId":"108938","playerOrTeamName":"MrBamLoL","leaguePoints":542,"rank":"I","wins":518,"losses":403,"veteran":true,"inactive":false,"freshBlood":false,"hotStreak":false},{"playerOrTeamId":"22499239","playerOrTeamName":"EVO Crysis","leaguePoints":925,"rank":"I","wins":237,"losses":131,"veteran":true,"inactive":false,"freshBlood":false,"hotStreak":false},{"playerOrTeamId":"19856613","playerOrTeamName":"Azridka","leaguePoints":852,"rank":"I","wins":284,"losses":193,"veteran":true,"inactive":false,"freshBlood":false,"hotStreak":true},{"playerOrTeamId":"45117472","playerOrTeamName":"ShinyStar","leaguePoints":518,"rank":"I","wins":321,"losses":249,"veteran":false,"inactive":false,"freshBlood":true,"hotStreak":false},{"playerOrTeamId":"33465281","playerOrTeamName":"iFeed4Boobs","leaguePoints":515,"rank":"I","wins":497,"losses":410,"veteran":false,"inactive":false,"freshBlood":true,"hotStreak":true},{"playerOrTeamId":"24529353","playerOrTeamName":"Jackboom","leaguePoints":515,"rank":"I","wins":236,"losses":171,"veteran":false,"inactive":false,"freshBlood":true,"hotStreak":true},{"playerOrTeamId":"84311039","playerOrTeamName":"JhinForThaWin","leaguePoints":679,"rank":"I","wins":170,"losses":87,"veteran":false,"inactive":false,"freshBlood":false,"hotStreak":false},{"playerOrTeamId":"24505220","playerOrTeamName":"Jimboom","leaguePoints":515,"rank":"I","wins":236,"losses":171,"veteran":false,"inactive":false,"freshBlood":true,"hotStreak":true},{"playerOrTeamId":"25270068","playerOrTeamName":"uMad my Day","leaguePoints":691,"rank":"I","wins":232,"losses":171,"veteran":true,"inactive":false,"freshBlood":false,"hotStreak":false},{"playerOrTeamId":"20870092","playerOrTeamName":"EVO Jünther","leaguePoints":640,"rank":"I","wins":180,"losses":108,"veteran":false,"inactive":false,"freshBlood":false,"hotStreak":false},{"playerOrTeamId":"20329178","playerOrTeamName":"Péter Zwégat","leaguePoints":560,"rank":"I","wins":211,"losses":122,"veteran":false,"inactive":false,"freshBlood":false,"hotStreak":true},{"playerOrTeamId":"22221330","playerOrTeamName":"Crimson ˉ","leaguePoints":522,"rank":"I","wins":135,"losses":84,"veteran":false,"inactive":false,"freshBlood":false,"hotStreak":false},{"playerOrTeamId":"19001663","playerOrTeamName":"Viktorwwe","leaguePoints":570,"rank":"I","wins":262,"losses":158,"veteran":false,"inactive":false,"freshBlood":false,"hotStreak":false},{"playerOrTeamId":"30817060","playerOrTeamName":"Keduris","leaguePoints":526,"rank":"I","wins":364,"losses":275,"veteran":false,"inactive":false,"freshBlood":false,"hotStreak":true},{"playerOrTeamId":"21721331","playerOrTeamName":"Hèisenbèrg","leaguePoints":703,"rank":"I","wins":407,"losses":248,"veteran":true,"inactive":false,"freshBlood":false,"hotStreak":true},{"playerOrTeamId":"43111230","playerOrTeamName":"cant believe","leaguePoints":529,"rank":"I","wins":320,"losses":244,"veteran":false,"inactive":false,"freshBlood":true,"hotStreak":true},{"playerOrTeamId":"21204161","playerOrTeamName":"EIIie00","leaguePoints":584,"rank":"I","wins":118,"losses":45,"veteran":false,"inactive":false,"freshBlood":false,"hotStreak":false},{"playerOrTeamId":"21528543","playerOrTeamName":"Bm04","leaguePoints":523,"rank":"I","wins":134,"losses":76,"veteran":false,"inactive":false,"freshBlood":false,"hotStreak":false},{"playerOrTeamId":"98738125","playerOrTeamName":"Woosahh","leaguePoints":566,"rank":"I","wins":94,"losses":42,"veteran":false,"inactive":false,"freshBlood":false,"hotStreak":false},{"playerOrTeamId":"28810393","playerOrTeamName":"Syyron","leaguePoints":1017,"rank":"I","wins":323,"losses":142,"veteran":true,"inactive":false,"freshBlood":false,"hotStreak":false},{"playerOrTeamId":"28881629","playerOrTeamName":"WOLVES Hero","leaguePoints":1226,"rank":"I","wins":420,"losses":236,"veteran":true,"inactive":false,"freshBlood":false,"hotStreak":true},{"playerOrTeamId":"31418271","playerOrTeamName":"N0OT N0OT ","leaguePoints":707,"rank":"I","wins":136,"losses":70,"veteran":false,"inactive":false,"freshBlood":false,"hotStreak":true},{"playerOrTeamId":"26252601","playerOrTeamName":"Zæƒø","leaguePoints":535,"rank":"I","wins":270,"losses":206,"veteran":true,"inactive":false,"freshBlood":false,"hotStreak":false},{"playerOrTeamId":"19805131","playerOrTeamName":"1UP Ghoul","leaguePoints":615,"rank":"I","wins":203,"losses":148,"veteran":false,"inactive":false,"freshBlood":false,"hotStreak":false},{"playerOrTeamId":"23972436","playerOrTeamName":"Inprato","leaguePoints":524,"rank":"I","wins":346,"losses":256,"veteran":false,"inactive":false,"freshBlood":false,"hotStreak":true},{"playerOrTeamId":"35142201","playerOrTeamName":"WãNTeD","leaguePoints":621,"rank":"I","wins":263,"losses":140,"veteran":true,"inactive":false,"freshBlood":false,"hotStreak":false},{"playerOrTeamId":"32027400","playerOrTeamName":"Cas","leaguePoints":928,"rank":"I","wins":283,"losses":164,"veteran":true,"inactive":false,"freshBlood":false,"hotStreak":false},{"playerOrTeamId":"35065234","playerOrTeamName":"Cute Bunny","leaguePoints":490,"rank":"I","wins":143,"losses":86,"veteran":true,"inactive":false,"freshBlood":false,"hotStreak":false},{"playerOrTeamId":"24409921","playerOrTeamName":"T JbK","leaguePoints":505,"rank":"I","wins":594,"losses":461,"veteran":false,"inactive":false,"freshBlood":true,"hotStreak":true},{"playerOrTeamId":"42067546","playerOrTeamName":"BattIeBunnyRïven","leaguePoints":545,"rank":"I","wins":161,"losses":115,"veteran":false,"inactive":false,"freshBlood":false,"hotStreak":false},{"playerOrTeamId":"101936935","playerOrTeamName":"T ºKP Stefan L","leaguePoints":530,"rank":"I","wins":94,"losses":37,"veteran":false,"inactive":false,"freshBlood":false,"hotStreak":false},{"playerOrTeamId":"27105957","playerOrTeamName":"Send it","leaguePoints":520,"rank":"I","wins":264,"losses":215,"veteran":false,"inactive":false,"freshBlood":false,"hotStreak":false},{"playerOrTeamId":"253574","playerOrTeamName":"muyuu","leaguePoints":538,"rank":"I","wins":110,"losses":63,"veteran":false,"inactive":false,"freshBlood":false,"hotStreak":false},{"playerOrTeamId":"28917173","playerOrTeamName":"Grabí","leaguePoints":529,"rank":"I","wins":190,"losses":117,"veteran":false,"inactive":false,"freshBlood":false,"hotStreak":true},{"playerOrTeamId":"19049292","playerOrTeamName":"Boph Teífong","leaguePoints":528,"rank":"I","wins":217,"losses":168,"veteran":false,"inactive":false,"freshBlood":true,"hotStreak":true},{"playerOrTeamId":"19950575","playerOrTeamName":"MästarMustachen","leaguePoints":599,"rank":"I","wins":188,"losses":115,"veteran":false,"inactive":false,"freshBlood":false,"hotStreak":false},{"playerOrTeamId":"19032197","playerOrTeamName":"Progressiv","leaguePoints":503,"rank":"I","wins":390,"losses":301,"veteran":false,"inactive":false,"freshBlood":false,"hotStreak":false},{"playerOrTeamId":"22588819","playerOrTeamName":"Xantiema","leaguePoints":520,"rank":"I","wins":270,"losses":183,"veteran":false,"inactive":false,"freshBlood":false,"hotStreak":false},{"playerOrTeamId":"31057640","playerOrTeamName":"RubioDBote","leaguePoints":553,"rank":"I","wins":157,"losses":85,"veteran":true,"inactive":false,"freshBlood":false,"hotStreak":false},{"playerOrTeamId":"100216812","playerOrTeamName":"ja se zovem Tim","leaguePoints":529,"rank":"I","wins":199,"losses":133,"veteran":false,"inactive":false,"freshBlood":false,"hotStreak":false},{"playerOrTeamId":"18993148","playerOrTeamName":"Rallexander","leaguePoints":562,"rank":"I","wins":221,"losses":151,"veteran":false,"inactive":false,"freshBlood":false,"hotStreak":true},{"playerOrTeamId":"24652910","playerOrTeamName":"MichaeI Scofield","leaguePoints":502,"rank":"I","wins":258,"losses":162,"veteran":true,"inactive":false,"freshBlood":false,"hotStreak":false}]}